LICENSE
README.md
setup.py
bin/kmergenetyper
kmergenetyper/__init__.py
kmergenetyper/kma.py
kmergenetyper/realignConsensus.py
kmergenetyper/typeGenes.py
kmergenetyper/version.py
kmergenetyper.egg-info/PKG-INFO
kmergenetyper.egg-info/SOURCES.txt
kmergenetyper.egg-info/dependency_links.txt
kmergenetyper.egg-info/top_level.txt