Metadata-Version: 2.1
Name: kmergenetyper
Version: 1.0.7
Summary: kmergenetyper - K-mer Gene Typer
Home-page: https://https://github.com/MBHallgren/kmergenetyper
Author: Malte B. Hallgren
Author-email: malhal@food.dtu.dk
License-File: LICENSE
